README.md
setup.py
examples/__init__.py
examples/example-classification.py
examples/example-segmentation.py
examples/palette.py
torchvision_enhance.egg-info/PKG-INFO
torchvision_enhance.egg-info/SOURCES.txt
torchvision_enhance.egg-info/dependency_links.txt
torchvision_enhance.egg-info/requires.txt
torchvision_enhance.egg-info/top_level.txt
torchvision_x/__init__.py
torchvision_x/datasets/__init__.py
torchvision_x/datasets/image_loader.py
torchvision_x/transforms/__init__.py
torchvision_x/transforms/functional.py
torchvision_x/transforms/transforms_cls.py
torchvision_x/transforms/transforms_seg.py