Metadata-Version: 1.0
Name: torchvision-enhance
Version: 0.1.3
Summary: Enhance torchvision for multi-channel images, 16-bit image, segmentation...
Home-page: https://github.com/sshuair/torchvision-enhance
Author: sshuair
Author-email: sshuair@gmail.com
License: UNKNOWN
Keywords: pytorch,vision,augmentation,deep learning
Platform: UNKNOWN
